acquantum_qiskit/__init__.py
acquantum_qiskit/_version.py
acquantum_qiskit/acquantumbackend.py
acquantum_qiskit/acquantumerrors.py
acquantum_qiskit/acquantumjob.py
acquantum_qiskit/acquantumprovider.py
acquantum_qiskit/acquantumsingleprovider.py
acquantum_qiskit/backendconfiguration.py
acquantum_qiskit/credentials/__init__.py
acquantum_qiskit/credentials/_env.py
acquantum_qiskit/models/Model.py
acquantum_qiskit/models/__init__.py
acquantum_qiskit-0.0.3.dist-info/DESCRIPTION.rst
acquantum_qiskit-0.0.3.dist-info/METADATA
acquantum_qiskit-0.0.3.dist-info/RECORD
acquantum_qiskit-0.0.3.dist-info/WHEEL
acquantum_qiskit-0.0.3.dist-info/metadata.json
acquantum_qiskit-0.0.3.dist-info/top_level.txt
