Metadata-Version: 2.0
Name: acquantum-qiskit
Version: 0.0.3
Summary: A qiskit provider for the Alibaba's quantum computer.
Home-page: https://github.com/carstenblank/acquantum_qiskit
Author: Carsten Blank
Author-email: blank@data-cybernetics.com
License: Apache 2.0
Platform: UNKNOWN
Classifier: Development Status :: 4 - Beta
Classifier: Programming Language :: Python :: 3
Classifier: Programming Language :: Python :: 3 :: Only
Classifier: License :: OSI Approved :: Apache Software License
Classifier: Operating System :: OS Independent
Requires-Dist: acquantum-connector (==0.0.5)
Requires-Dist: jsonschema (<2.7)
Requires-Dist: marshmallow
Requires-Dist: python-dateutil
Requires-Dist: qiskit (==0.7.0)
